{"2606.17820": {"publish_time": "2026-06-16", "title": "Improving low-resource ASR using bilingual fine-tuning with language identification: a cross-linguistic evaluation", "paper_summary": "This study explores how bilingual fine-tuning affects automatic speech recognition (ASR) in low-resource languages. We evaluate this method across nine linguistically and geographically diverse language pairs, covering a range of language families and writing systems. To distinguish the two languages, during training, we pre-pend each input text with a language identification token. At inference, the model jointly predicts both the language and transcription from the speech input alone. As texts for which the language is incorrectly determined show low ASR performance, we also conduct a follow-up experiment in which the language identification token is provided both during training and inference. Our results show that bilingual fine-tuning can be beneficial when language identification accuracy is high, and that in cases where language identification performance is low, including the language identification token at inference helps to improve ASR performance.", "paper_summary_zh": "\u9019\u9805\u7814\u7a76\u63a2\u8a0e\u4e86\u96d9\u8a9e\u5fae\u8abf\u5982\u4f55\u5f71\u97ff\u4f4e\u8cc7\u6e90\u8a9e\u8a00\u7684\u81ea\u52d5\u8a9e\u97f3\u8b58\u5225\uff08ASR\uff09\u3002<lb/>\u6211\u5011\u5728\u4e5d\u5c0d\u8a9e\u8a00\u4e0a\u8a55\u4f30\u9019\u7a2e\u65b9\u6cd5\uff0c\u9019\u4e9b\u8a9e\u8a00\u5728\u8a9e\u8a00\u5b78\u548c\u5730\u7406\u4e0a\u5177\u6709\u591a\u6a23\u6027\uff0c\u6db5\u84cb\u4e86\u591a\u7a2e\u8a9e\u8a00\u5bb6\u65cf\u548c\u66f8\u5beb\u7cfb\u7d71\u3002<lb/>\u70ba\u4e86\u5340\u5206\u9019\u5169\u7a2e\u8a9e\u8a00\uff0c\u5728\u8a13\u7df4\u671f\u9593\uff0c\u6211\u5011\u5728\u6bcf\u500b\u8f38\u5165\u6587\u672c\u524d\u6dfb\u52a0\u4e86\u4e00\u500b\u8a9e\u8a00\u8b58\u5225\u6a19\u8a18\u3002<lb/>\u5728\u63a8\u7406\u968e\u6bb5\uff0c\u6a21\u578b\u50c5\u6839\u64da\u8a9e\u97f3\u8f38\u5165\u5171\u540c\u9810\u6e2c\u8a9e\u8a00\u548c\u8f49\u9304\u3002<lb/>\u7531\u65bc\u8a9e\u8a00\u8b58\u5225\u932f\u8aa4\u7684\u6587\u672c\u986f\u793a\u51fa\u4f4eASR\u6027\u80fd\uff0c\u6211\u5011\u9084\u9032\u884c\u4e86\u4e00\u500b\u5f8c\u7e8c\u5be6\u9a57\uff0c\u5728\u8a72\u5be6\u9a57\u4e2d\uff0c\u5728\u8a13\u7df4\u548c\u63a8\u7406\u671f\u9593\u90fd\u63d0\u4f9b\u8a9e\u8a00\u8b58\u5225\u6a19\u8a18\u3002<lb/>\u6211\u5011\u7684\u7d50\u679c\u986f\u793a\uff0c\u7576\u8a9e\u8a00\u8b58\u5225\u6e96\u78ba\u6027\u9ad8\u6642\uff0c\u96d9\u8a9e\u5fae\u8abf\u662f\u6709\u76ca\u7684\uff0c\u800c\u5728\u8a9e\u8a00\u8b58\u5225\u6027\u80fd\u8f03\u4f4e\u7684\u60c5\u6cc1\u4e0b\uff0c\u5728\u63a8\u7406\u4e2d\u5305\u542b\u8a9e\u8a00\u8b58\u5225\u6a19\u8a18\u6709\u52a9\u65bc\u63d0\u9ad8ASR\u6027\u80fd\u3002", "author": "Reihaneh Amooie et.al.", "authors": "Reihaneh Amooie, Yun Hao, Wietse de Vries, Jelske Dijkstra, Matt Coler, Martijn Wieling", "id": "2606.17820v1", "paper_url": "http://arxiv.org/abs/2606.17820v1", "repo": "null"}}