{"2603.09192": {"publish_time": "2026-03-10", "title": "Explainable Innovation Engine: Dual-Tree Agent-RAG with Methods-as-Nodes and Verifiable Write-Back", "paper_summary": "Retrieval-augmented generation (RAG) improves factual grounding, yet most systems rely on flat chunk retrieval and provide limited control over multi-step synthesis. We propose an Explainable Innovation Engine that upgrades the knowledge unit from text chunks to methods-as-nodes. The engine maintains a weighted method provenance tree for traceable derivations and a hierarchical clustering abstraction tree for efficient top-down navigation. At inference time, a strategy agent selects explicit synthesis operators (e.g., induction, deduction, analogy), composes new method nodes, and records an auditable trajectory. A verifier-scorer layer then prunes low-quality candidates and writes validated nodes back to support continual growth. Expert evaluation across six domains and multiple backbones shows consistent gains over a vanilla baseline, with the largest improvements on derivation-heavy settings, and ablations confirm the complementary roles of provenance backtracking and pruning. These results suggest a practical path toward controllable, explainable, and verifiable innovation in agentic RAG systems. Code is available at the project GitHub repository https://github.com/xiaolu-666113/Dual-Tree-Agent-RAG.", "paper_summary_zh": "\u6aa2\u7d22\u589e\u5f37\u751f\u6210\uff08RAG\uff09\u6539\u5584\u4e86\u4e8b\u5be6\u57fa\u790e\uff0c\u4f46\u5927\u591a\u6578\u7cfb\u7d71\u4f9d\u8cf4\u65bc\u5e73\u9762\u584a\u6aa2\u7d22\uff0c\u4e26\u4e14\u5c0d\u591a\u6b65\u5408\u6210\u63d0\u4f9b\u6709\u9650\u7684\u63a7\u5236\u3002\u6211\u5011\u63d0\u51fa\u4e86\u4e00\u500b\u53ef\u89e3\u91cb\u7684\u5275\u65b0\u5f15\u64ce\uff0c\u5c07\u77e5\u8b58\u55ae\u5143\u5f9e\u6587\u672c\u584a\u5347\u7d1a\u70ba\u65b9\u6cd5\u4f5c\u70ba\u7bc0\u9ede\u3002\u8a72\u5f15\u64ce\u7dad\u8b77\u4e00\u500b\u52a0\u6b0a\u7684\u65b9\u6cd5\u4f86\u6e90\u6a39\uff0c\u4ee5\u4fbf\u65bc\u53ef\u8ffd\u6eaf\u7684\u63a8\u5c0e\uff0c\u4e26\u4e14\u6709\u4e00\u500b\u5c64\u6b21\u805a\u985e\u62bd\u8c61\u6a39\uff0c\u4ee5\u4fbf\u65bc\u9ad8\u6548\u7684\u81ea\u4e0a\u800c\u4e0b\u5c0e\u822a\u3002\u5728\u63a8\u7406\u6642\uff0c\u7b56\u7565\u4ee3\u7406\u9078\u64c7\u660e\u78ba\u7684\u5408\u6210\u64cd\u4f5c\u7b26\uff08\u4f8b\u5982\uff0c\u6b78\u7d0d\u3001\u6f14\u7e79\u3001\u985e\u6bd4\uff09\uff0c\u7d44\u5408\u65b0\u7684\u65b9\u6cd5\u7bc0\u9ede\uff0c\u4e26\u8a18\u9304\u53ef\u5be9\u8a08\u7684\u8ecc\u8de1\u3002\u7136\u5f8c\uff0c\u4e00\u500b\u9a57\u8b49\u8005-\u8a55\u5206\u5c64\u4fee\u526a\u4f4e\u8cea\u91cf\u5019\u9078\u8005\uff0c\u4e26\u5c07\u9a57\u8b49\u904e\u7684\u7bc0\u9ede\u5beb\u56de\u4ee5\u652f\u6301\u6301\u7e8c\u589e\u9577\u3002\u5728\u516d\u500b\u9818\u57df\u548c\u591a\u500b\u9aa8\u5e79\u4e0a\u7684\u5c08\u5bb6\u8a55\u4f30\u986f\u793a\uff0c\u76f8\u8f03\u65bc\u666e\u901a\u57fa\u6e96\u6709\u4e00\u81f4\u7684\u589e\u76ca\uff0c\u4e26\u4e14\u5728\u63a8\u5c0e\u5bc6\u96c6\u7684\u8a2d\u7f6e\u4e2d\u6709\u6700\u5927\u7684\u6539\u5584\uff0c\u6d88\u878d\u5be6\u9a57\u78ba\u8a8d\u4e86\u4f86\u6e90\u56de\u6eaf\u548c\u4fee\u526a\u7684\u4e92\u88dc\u89d2\u8272\u3002\u9019\u4e9b\u7d50\u679c\u8868\u660e\uff0c\u671d\u8457\u53ef\u63a7\u3001\u53ef\u89e3\u91cb\u548c\u53ef\u9a57\u8b49\u7684\u5275\u65b0\u5728\u4ee3\u7406RAG\u7cfb\u7d71\u4e2d\u63d0\u4f9b\u4e86\u4e00\u689d\u5be6\u7528\u7684\u9053\u8def\u3002\u4ee3\u78bc\u53ef\u5728\u9805\u76eeGitHub\u5eab https://github.com/xiaolu-666113/Dual-Tree-Agent-RAG \u7372\u5f97\u3002", "author": "Renwei Meng et.al.", "authors": "Renwei Meng", "id": "2603.09192v1", "paper_url": "http://arxiv.org/abs/2603.09192v1", "repo": "null"}}