{"2405.17116": {"publish_time": "2024-05-27", "title": "Mixtures of Unsupervised Lexicon Classification", "paper_summary": "This paper presents a mixture version of the method-of-moment unsupervised\nlexicon classification by an incorporation of a Dirichlet process.", "paper_summary_zh": "\u672c\u6587\u63d0\u51fa\u4e86\u4e00\u500b\u65b9\u6cd5\u77e9\u7121\u76e3\u7763\u8a5e\u5f59\u5206\u985e\u7684\u6df7\u5408\u7248\u672c\uff0c\u4e26\u7d50\u5408\u4e86\u72c4\u5229\u514b\u96f7\u904e\u7a0b\u3002", "author": "Peratham Wiriyathammabhum et.al.", "authors": "Peratham Wiriyathammabhum", "id": "2405.17116v1", "paper_url": "http://arxiv.org/abs/2405.17116v1", "repo": "null"}}