{"2406.18354": {"publish_time": "2024-06-26", "title": "Kolmogorov-Arnold Graph Neural Networks", "paper_summary": "Graph neural networks (GNNs) excel in learning from network-like data but\noften lack interpretability, making their application challenging in domains\nrequiring transparent decision-making. We propose the Graph Kolmogorov-Arnold\nNetwork (GKAN), a novel GNN model leveraging spline-based activation functions\non edges to enhance both accuracy and interpretability. Our experiments on five\nbenchmark datasets demonstrate that GKAN outperforms state-of-the-art GNN\nmodels in node classification, link prediction, and graph classification tasks.\nIn addition to the improved accuracy, GKAN's design inherently provides clear\ninsights into the model's decision-making process, eliminating the need for\npost-hoc explainability techniques. This paper discusses the methodology,\nperformance, and interpretability of GKAN, highlighting its potential for\napplications in domains where interpretability is crucial.", "paper_summary_zh": "\u5716\u5f62\u795e\u7d93\u7db2\u8def (GNN) \u64c5\u9577\u5f9e\u7db2\u8def\u72c0\u8cc7\u6599\u5b78\u7fd2\uff0c\u4f46\u901a\u5e38\u7f3a\u4e4f\u53ef\u89e3\u91cb\u6027\uff0c\u9019\u4f7f\u5f97\u5b83\u5011\u5728\u9700\u8981\u900f\u660e\u6c7a\u7b56\u7684\u9818\u57df\u4e2d\u61c9\u7528\u5177\u6709\u6311\u6230\u6027\u3002\u6211\u5011\u63d0\u51fa\u5716\u5f62 Kolmogorov-Arnold \u7db2\u8def (GKAN)\uff0c\u9019\u662f\u4e00\u7a2e\u65b0\u7a4e\u7684 GNN \u6a21\u578b\uff0c\u5728\u908a\u7de3\u4e0a\u5229\u7528\u57fa\u65bc\u6a23\u689d\u7684\u6fc0\u6d3b\u51fd\u6578\u4f86\u589e\u5f37\u6e96\u78ba\u6027\u548c\u53ef\u89e3\u91cb\u6027\u3002\u6211\u5011\u5728\u4e94\u500b\u57fa\u6e96\u8cc7\u6599\u96c6\u4e0a\u7684\u5be6\u9a57\u8868\u660e\uff0cGKAN \u5728\u7bc0\u9ede\u5206\u985e\u3001\u9023\u7d50\u9810\u6e2c\u548c\u5716\u5f62\u5206\u985e\u4efb\u52d9\u4e2d\u512a\u65bc\u6700\u5148\u9032\u7684 GNN \u6a21\u578b\u3002\u9664\u4e86\u63d0\u9ad8\u6e96\u78ba\u6027\u4e4b\u5916\uff0cGKAN \u7684\u8a2d\u8a08\u672c\u8eab\u5c31\u5c0d\u6a21\u578b\u7684\u6c7a\u7b56\u904e\u7a0b\u63d0\u4f9b\u4e86\u6e05\u6670\u7684\u898b\u89e3\uff0c\u6d88\u9664\u4e86\u5c0d\u4e8b\u5f8c\u53ef\u89e3\u91cb\u6027\u6280\u8853\u7684\u9700\u6c42\u3002\u672c\u6587\u8a0e\u8ad6\u4e86 GKAN \u7684\u65b9\u6cd5\u3001\u6027\u80fd\u548c\u53ef\u89e3\u91cb\u6027\uff0c\u5f37\u8abf\u4e86\u5176\u5728\u53ef\u89e3\u91cb\u6027\u81f3\u95dc\u91cd\u8981\u7684\u9818\u57df\u4e2d\u7684\u61c9\u7528\u6f5b\u529b\u3002", "author": "Gianluca De Carlo et.al.", "authors": "Gianluca De Carlo, Andrea Mastropietro, Aris Anagnostopoulos", "id": "2406.18354v1", "paper_url": "http://arxiv.org/abs/2406.18354v1", "repo": "null"}}