{"2406.08374": {"publish_time": "2024-06-12", "title": "2.5D Multi-view Averaging Diffusion Model for 3D Medical Image Translation: Application to Low-count PET Reconstruction with CT-less Attenuation Correction", "paper_summary": "Positron Emission Tomography (PET) is an important clinical imaging tool but\ninevitably introduces radiation hazards to patients and healthcare providers.\nReducing the tracer injection dose and eliminating the CT acquisition for\nattenuation correction can reduce the overall radiation dose, but often results\nin PET with high noise and bias. Thus, it is desirable to develop 3D methods to\ntranslate the non-attenuation-corrected low-dose PET (NAC-LDPET) into\nattenuation-corrected standard-dose PET (AC-SDPET). Recently, diffusion models\nhave emerged as a new state-of-the-art deep learning method for image-to-image\ntranslation, better than traditional CNN-based methods. However, due to the\nhigh computation cost and memory burden, it is largely limited to 2D\napplications. To address these challenges, we developed a novel 2.5D Multi-view\nAveraging Diffusion Model (MADM) for 3D image-to-image translation with\napplication on NAC-LDPET to AC-SDPET translation. Specifically, MADM employs\nseparate diffusion models for axial, coronal, and sagittal views, whose outputs\nare averaged in each sampling step to ensure the 3D generation quality from\nmultiple views. To accelerate the 3D sampling process, we also proposed a\nstrategy to use the CNN-based 3D generation as a prior for the diffusion model.\nOur experimental results on human patient studies suggested that MADM can\ngenerate high-quality 3D translation images, outperforming previous CNN-based\nand Diffusion-based baseline methods.", "paper_summary_zh": "\u6b63\u5b50\u767c\u5c04\u65b7\u5c64\u6383\u63cf (PET) \u662f\u4e00\u7a2e\u91cd\u8981\u7684\u81e8\u5e8a\u5f71\u50cf\u5de5\u5177\uff0c\u4f46\u4e0d\u53ef\u907f\u514d\u5730\u6703\u5c0d\u60a3\u8005\u548c\u91ab\u7642\u4fdd\u5065\u63d0\u4f9b\u8005\u9020\u6210\u8f3b\u5c04\u5371\u5bb3\u3002\u964d\u4f4e\u793a\u8e64\u5291\u6ce8\u5c04\u5291\u91cf\u4e26\u6d88\u9664\u96fb\u8166\u65b7\u5c64\u6383\u63cf\u4ee5\u9032\u884c\u8870\u6e1b\u6821\u6b63\u53ef\u4ee5\u964d\u4f4e\u6574\u9ad4\u8f3b\u5c04\u5291\u91cf\uff0c\u4f46\u901a\u5e38\u6703\u5c0e\u81f4 PET \u7522\u751f\u9ad8\u96dc\u8a0a\u548c\u504f\u5dee\u3002\u56e0\u6b64\uff0c\u958b\u767c 3D \u65b9\u6cd5\u5c07\u975e\u8870\u6e1b\u6821\u6b63\u4f4e\u5291\u91cf PET (NAC-LDPET) \u8f49\u63db\u70ba\u8870\u6e1b\u6821\u6b63\u6a19\u6e96\u5291\u91cf PET (AC-SDPET) \u662f\u5f88\u91cd\u8981\u7684\u3002\u6700\u8fd1\uff0c\u64f4\u6563\u6a21\u578b\u5df2\u6210\u70ba\u4e00\u7a2e\u65b0\u7684\u6700\u5148\u9032\u7684\u6df1\u5ea6\u5b78\u7fd2\u65b9\u6cd5\uff0c\u7528\u65bc\u5f71\u50cf\u8f49\u63db\u5f71\u50cf\uff0c\u512a\u65bc\u50b3\u7d71\u7684\u57fa\u65bc CNN \u7684\u65b9\u6cd5\u3002\u7136\u800c\uff0c\u7531\u65bc\u9ad8\u904b\u7b97\u6210\u672c\u548c\u8a18\u61b6\u9ad4\u8ca0\u64d4\uff0c\u5b83\u5728\u5f88\u5927\u7a0b\u5ea6\u4e0a\u50c5\u9650\u65bc 2D \u61c9\u7528\u7a0b\u5f0f\u3002\u70ba\u4e86\u61c9\u5c0d\u9019\u4e9b\u6311\u6230\uff0c\u6211\u5011\u958b\u767c\u4e86\u4e00\u7a2e\u65b0\u7a4e\u7684 2.5D \u591a\u8996\u5716\u5e73\u5747\u64f4\u6563\u6a21\u578b (MADM)\uff0c\u7528\u65bc 3D \u5f71\u50cf\u8f49\u63db\u5f71\u50cf\uff0c\u4e26\u61c9\u7528\u65bc NAC-LDPET \u8f49\u63db\u70ba AC-SDPET\u3002\u5177\u9ad4\u4f86\u8aaa\uff0cMADM \u70ba\u8ef8\u5411\u3001\u51a0\u72c0\u548c\u77e2\u72c0\u8996\u5716\u63a1\u7528\u4e86\u55ae\u7368\u7684\u64f4\u6563\u6a21\u578b\uff0c\u5176\u8f38\u51fa\u5728\u6bcf\u500b\u63a1\u6a23\u6b65\u9a5f\u4e2d\u53d6\u5e73\u5747\u503c\uff0c\u4ee5\u78ba\u4fdd\u5f9e\u591a\u500b\u8996\u5716\u4e2d\u9032\u884c 3D \u751f\u6210\u54c1\u8cea\u3002\u70ba\u4e86\u52a0\u901f 3D \u63a1\u6a23\u904e\u7a0b\uff0c\u6211\u5011\u9084\u63d0\u51fa\u4e86\u4e00\u7a2e\u7b56\u7565\uff0c\u5c07\u57fa\u65bc CNN \u7684 3D \u751f\u6210\u7528\u4f5c\u64f4\u6563\u6a21\u578b\u7684\u5148\u9a57\u3002\u6211\u5011\u5728\u4eba\u9ad4\u60a3\u8005\u7814\u7a76\u4e2d\u5f97\u5230\u7684\u5be6\u9a57\u7d50\u679c\u8868\u660e\uff0cMADM \u53ef\u4ee5\u751f\u6210\u9ad8\u54c1\u8cea\u7684 3D \u8f49\u63db\u5f71\u50cf\uff0c\u512a\u65bc\u5148\u524d\u7684\u57fa\u65bc CNN \u548c\u57fa\u65bc\u64f4\u6563\u7684\u57fa\u7dda\u65b9\u6cd5\u3002", "author": "Tianqi Chen et.al.", "authors": "Tianqi Chen, Jun Hou, Yinchi Zhou, Huidong Xie, Xiongchao Chen, Qiong Liu, Xueqi Guo, Menghua Xia, James S. Duncan, Chi Liu, Bo Zhou", "id": "2406.08374v1", "paper_url": "http://arxiv.org/abs/2406.08374v1", "repo": "null"}}