{"2412.02012": {"publish_time": "2024-12-02", "title": "INSIGHT: Explainable Weakly-Supervised Medical Image Analysis", "paper_summary": "Due to their large sizes, volumetric scans and whole-slide pathology images\n(WSIs) are often processed by extracting embeddings from local regions and then\nan aggregator makes predictions from this set. However, current methods require\npost-hoc visualization techniques (e.g., Grad-CAM) and often fail to localize\nsmall yet clinically crucial details. To address these limitations, we\nintroduce INSIGHT, a novel weakly-supervised aggregator that integrates heatmap\ngeneration as an inductive bias. Starting from pre-trained feature maps,\nINSIGHT employs a detection module with small convolutional kernels to capture\nfine details and a context module with a broader receptive field to suppress\nlocal false positives. The resulting internal heatmap highlights diagnostically\nrelevant regions. On CT and WSI benchmarks, INSIGHT achieves state-of-the-art\nclassification results and high weakly-labeled semantic segmentation\nperformance. Project website and code are available at:\nhttps://zhangdylan83.github.io/ewsmia/", "paper_summary_zh": "\u7531\u65bc\u9ad4\u7a4d\u9f90\u5927\uff0c\u9ad4\u7a4d\u6383\u63cf\u548c\u5168\u73bb\u7247\u75c5\u7406\u5716\u50cf (WSI) \u901a\u5e38\u6703\u900f\u904e\u5f9e\u5c40\u90e8\u5340\u57df\u64f7\u53d6\u5d4c\u5165\u5f0f\u8655\u7406\uff0c\u7136\u5f8c\u805a\u5408\u5668\u6703\u6839\u64da\u9019\u7d44\u8cc7\u6599\u9032\u884c\u9810\u6e2c\u3002\u7136\u800c\uff0c\u76ee\u524d\u7684\u65b9\u6cd5\u9700\u8981\u4e8b\u5f8c\u8996\u89ba\u5316\u6280\u8853\uff08\u4f8b\u5982 Grad-CAM\uff09\uff0c\u800c\u4e14\u5f80\u5f80\u7121\u6cd5\u5b9a\u4f4d\u96d6\u7136\u7d30\u5fae\u4f46\u81e8\u5e8a\u4e0a\u81f3\u95dc\u91cd\u8981\u7684\u7d30\u7bc0\u3002\u70ba\u4e86\u89e3\u6c7a\u9019\u4e9b\u9650\u5236\uff0c\u6211\u5011\u5f15\u5165\u4e86 INSIGHT\uff0c\u9019\u662f\u4e00\u7a2e\u65b0\u7a4e\u7684\u5f31\u76e3\u7763\u805a\u5408\u5668\uff0c\u53ef\u5c07\u71b1\u5716\u751f\u6210\u6574\u5408\u70ba\u6b78\u7d0d\u504f\u5dee\u3002INSIGHT \u5f9e\u9810\u5148\u8a13\u7df4\u597d\u7684\u7279\u5fb5\u5716\u958b\u59cb\uff0c\u63a1\u7528\u5177\u6709\u5c0f\u578b\u5377\u7a4d\u6838\u7684\u5075\u6e2c\u6a21\u7d44\u4f86\u64f7\u53d6\u7cbe\u7d30\u7684\u7d30\u7bc0\uff0c\u4e26\u63a1\u7528\u5177\u6709\u8f03\u5ee3\u6cdb\u611f\u53d7\u91ce\u7684\u5167\u5bb9\u6a21\u7d44\u4f86\u6291\u5236\u5c40\u90e8\u8aa4\u5224\u3002\u7522\u751f\u7684\u5167\u90e8\u71b1\u5716\u7a81\u986f\u4e86\u8a3a\u65b7\u76f8\u95dc\u7684\u5340\u57df\u3002\u5728 CT \u548c WSI \u57fa\u6e96\u4e0a\uff0cINSIGHT \u9054\u5230\u4e86\u6700\u5148\u9032\u7684\u5206\u985e\u7d50\u679c\uff0c\u4e26\u5177\u5099\u9ad8\u5ea6\u5f31\u6a19\u8a18\u8a9e\u610f\u5206\u5272\u6548\u80fd\u3002\u5c08\u6848\u7db2\u7ad9\u548c\u7a0b\u5f0f\u78bc\u53ef\u65bc\u4e0b\u5217\u7db2\u5740\u53d6\u5f97\uff1a\nhttps://zhangdylan83.github.io/ewsmia/", "author": "Wenbo Zhang et.al.", "authors": "Wenbo Zhang, Junyu Chen, Christopher Kanan", "id": "2412.02012v1", "paper_url": "http://arxiv.org/abs/2412.02012v1", "repo": "null"}}