{"2407.19984": {"publish_time": "2024-07-29", "title": "Confidence Estimation for Automatic Detection of Depression and Alzheimer's Disease Based on Clinical Interviews", "paper_summary": "Speech-based automatic detection of Alzheimer's disease (AD) and depression\nhas attracted increased attention. Confidence estimation is crucial for a\ntrust-worthy automatic diagnostic system which informs the clinician about the\nconfidence of model predictions and helps reduce the risk of misdiagnosis. This\npaper investigates confidence estimation for automatic detection of AD and\ndepression based on clinical interviews. A novel Bayesian approach is proposed\nwhich uses a dynamic Dirichlet prior distribution to model the second-order\nprobability of the predictive distribution. Experimental results on the\npublicly available ADReSS and DAIC-WOZ datasets demonstrate that the proposed\nmethod outperforms a range of baselines for both classification accuracy and\nconfidence estimation.", "paper_summary_zh": "\u57fa\u65bc\u8a9e\u8a00\u7684\u963f\u8332\u6d77\u9ed8\u75c7 (AD) \u548c\u6182\u9b31\u75c7\u81ea\u52d5\u5075\u6e2c\u5f15\u8d77\u4e86\u66f4\u591a\u95dc\u6ce8\u3002\u5c0d\u65bc\u4e00\u500b\u503c\u5f97\u4fe1\u8cf4\u7684\u81ea\u52d5\u8a3a\u65b7\u7cfb\u7d71\u800c\u8a00\uff0c\u4fe1\u5fc3\u4f30\u8a08\u81f3\u95dc\u91cd\u8981\uff0c\u5b83\u6703\u544a\u77e5\u81e8\u5e8a\u91ab\u751f\u6a21\u578b\u9810\u6e2c\u7684\u4fe1\u5fc3\u4e26\u6709\u52a9\u65bc\u964d\u4f4e\u8aa4\u8a3a\u98a8\u96aa\u3002\u672c\u6587\u63a2\u8a0e\u4e86\u57fa\u65bc\u81e8\u5e8a\u8a2a\u8ac7\u5c0d AD \u548c\u6182\u9b31\u75c7\u9032\u884c\u81ea\u52d5\u5075\u6e2c\u7684\u4fe1\u5fc3\u4f30\u8a08\u3002\u63d0\u51fa\u4e86\u4e00\u7a2e\u65b0\u7684\u8c9d\u6c0f\u65b9\u6cd5\uff0c\u5b83\u4f7f\u7528\u52d5\u614b Dirichlet \u5148\u9a57\u5206\u4f48\u4f86\u5c0d\u9810\u6e2c\u5206\u4f48\u7684\u4e8c\u968e\u6a5f\u7387\u9032\u884c\u5efa\u6a21\u3002\u5728\u516c\u958b\u7684 ADReSS \u548c DAIC-WOZ \u8cc7\u6599\u96c6\u4e0a\u7684\u5be6\u9a57\u7d50\u679c\u8868\u660e\uff0c\u6240\u63d0\u51fa\u7684\u65b9\u6cd5\u5728\u5206\u985e\u6e96\u78ba\u5ea6\u548c\u4fe1\u5fc3\u4f30\u8a08\u65b9\u9762\u512a\u65bc\u4e00\u7cfb\u5217\u57fa\u6e96\u3002", "author": "Wen Wu et.al.", "authors": "Wen Wu, Chao Zhang, Philip C. Woodland", "id": "2407.19984v1", "paper_url": "http://arxiv.org/abs/2407.19984v1", "repo": "null"}}