{"2406.08173": {"publish_time": "2024-06-12", "title": "Semi-Supervised Spoken Language Glossification", "paper_summary": "Spoken language glossification (SLG) aims to translate the spoken language\ntext into the sign language gloss, i.e., a written record of sign language. In\nthis work, we present a framework named $S$emi-$S$upervised $S$poken $L$anguage\n$G$lossification ($S^3$LG) for SLG. To tackle the bottleneck of limited\nparallel data in SLG, our $S^3$LG incorporates large-scale monolingual spoken\nlanguage text into SLG training. The proposed framework follows the\nself-training structure that iteratively annotates and learns from pseudo\nlabels. Considering the lexical similarity and syntactic difference between\nsign language and spoken language, our $S^3$LG adopts both the rule-based\nheuristic and model-based approach for auto-annotation. During training, we\nrandomly mix these complementary synthetic datasets and mark their differences\nwith a special token. As the synthetic data may be less quality, the $S^3$LG\nfurther leverages consistency regularization to reduce the negative impact of\nnoise in the synthetic data. Extensive experiments are conducted on public\nbenchmarks to demonstrate the effectiveness of the $S^3$LG. Our code is\navailable at \\url{https://github.com/yaohj11/S3LG}.", "paper_summary_zh": "\u53e3\u8a9e\u5316\u6a19\u8a18 (SLG) \u65e8\u5728\u5c07\u53e3\u8a9e\u6587\u672c\u7ffb\u8b6f\u6210\u624b\u8a9e\u6a19\u8a18\uff0c\u5373\u624b\u8a9e\u7684\u66f8\u9762\u8a18\u9304\u3002\u5728\u9019\u9805\u5de5\u4f5c\u4e2d\uff0c\u6211\u5011\u63d0\u51fa\u4e86\u4e00\u500b\u540d\u70ba $S$emi-$S$upervised $S$poken $L$anguage $G$lossification ($S^3$LG) \u7684 SLG \u6846\u67b6\u3002\u70ba\u4e86\u89e3\u6c7a SLG \u4e2d\u4e26\u884c\u6578\u64da\u6709\u9650\u7684\u74f6\u9838\uff0c\u6211\u5011\u7684 $S^3$LG \u5c07\u5927\u898f\u6a21\u55ae\u8a9e\u53e3\u8a9e\u6587\u672c\u7d0d\u5165 SLG \u8a13\u7df4\u4e2d\u3002\u6240\u63d0\u51fa\u7684\u6846\u67b6\u9075\u5faa\u81ea\u8a13\u7df4\u7d50\u69cb\uff0c\u53cd\u8986\u6a19\u8a18\u4e26\u5f9e\u507d\u6a19\u7c64\u4e2d\u5b78\u7fd2\u3002\u8003\u616e\u5230\u624b\u8a9e\u548c\u53e3\u8a9e\u4e4b\u9593\u7684\u8a5e\u5f59\u76f8\u4f3c\u6027\u548c\u53e5\u6cd5\u5dee\u7570\uff0c\u6211\u5011\u7684 $S^3$LG \u63a1\u7528\u57fa\u65bc\u898f\u5247\u7684\u555f\u767c\u5f0f\u65b9\u6cd5\u548c\u57fa\u65bc\u6a21\u578b\u7684\u65b9\u6cd5\u9032\u884c\u81ea\u52d5\u6a19\u8a18\u3002\u5728\u8a13\u7df4\u671f\u9593\uff0c\u6211\u5011\u96a8\u6a5f\u6df7\u5408\u9019\u4e9b\u4e92\u88dc\u7684\u5408\u6210\u6578\u64da\u96c6\uff0c\u4e26\u7528\u7279\u6b8a\u4ee4\u724c\u6a19\u8a18\u5b83\u5011\u7684\u5dee\u7570\u3002\u7531\u65bc\u5408\u6210\u6578\u64da\u7684\u54c1\u8cea\u53ef\u80fd\u8f03\u5dee\uff0c\u56e0\u6b64 $S^3$LG \u9032\u4e00\u6b65\u5229\u7528\u4e00\u81f4\u6027\u6b63\u5247\u5316\u4f86\u6e1b\u5c11\u5408\u6210\u6578\u64da\u4e2d\u96dc\u8a0a\u7684\u8ca0\u9762\u5f71\u97ff\u3002\u5728\u516c\u5171\u57fa\u6e96\u4e0a\u9032\u884c\u4e86\u5ee3\u6cdb\u7684\u5be6\u9a57\uff0c\u4ee5\u8b49\u660e $S^3$LG \u7684\u6709\u6548\u6027\u3002\u6211\u5011\u7684\u7a0b\u5f0f\u78bc\u53ef\u5728 \\url{https://github.com/yaohj11/S3LG} \u53d6\u5f97\u3002", "author": "Huijie Yao et.al.", "authors": "Huijie Yao, Wengang Zhou, Hao Zhou, Houqiang Li", "id": "2406.08173v1", "paper_url": "http://arxiv.org/abs/2406.08173v1", "repo": "https://github.com/yaohj11/s3lg"}}