{"2604.26508": {"publish_time": "2026-04-29", "title": "Progressive Semantic Communication for Efficient Edge-Cloud Vision-Language Models", "paper_summary": "Deploying Vision-Language Models (VLMs) on edge devices remains challenging due to their substantial computational and memory demands, which exceed the capabilities of resource-constrained embedded platforms. Conversely, fully offloading inference to the cloud is often impractical in bandwidth-limited environments, where transmitting raw visual data introduces substantial latency overhead. While recent edge-cloud collaborative architectures attempt to partition VLM workloads across devices, they typically rely on transmitting fixed-size representations, lacking adaptability to dynamic network conditions and failing to fully exploit semantic redundancy. In this paper, we propose a progressive semantic communication framework for edge-cloud VLM inference, using a Meta AutoEncoder that compresses visual tokens into adaptive, progressively refinable representations, enabling plug-and-play deployment with off-the-shelf VLMs without additional fine-tuning. This design allows flexible transmission at different information levels, providing a controllable trade-off between communication cost and semantic fidelity. We implement a full end-to-end edge-cloud system comprising an embedded NXP i.MX95 platform and a GPU server, communicating over bandwidth-constrained networks. Experimental results show that, at 1 Mbps uplink, the proposed progressive scheme significantly reduces network latency compared to full-edge and full-cloud solutions, while maintaining high semantic consistency even under high compression. The implementation code will be released upon publication at https://github.com/open-ep/ProSemComVLM.", "paper_summary_zh": "\u5728\u908a\u7de3\u8a2d\u5099\u4e0a\u90e8\u7f72\u8996\u89ba-\u8a9e\u8a00\u6a21\u578b\uff08VLM\uff09\u4ecd\u7136\u5177\u6709\u6311\u6230\u6027\uff0c\u56e0\u70ba\u5176\u9f90\u5927\u7684\u8a08\u7b97\u548c\u8a18\u61b6\u9ad4\u9700\u6c42\u8d85\u51fa\u4e86\u8cc7\u6e90\u53d7\u9650\u7684\u5d4c\u5165\u5f0f\u5e73\u53f0\u7684\u80fd\u529b\u3002\u76f8\u53cd\uff0c\u5c07\u63a8\u65b7\u5b8c\u5168\u5378\u8f09\u5230\u96f2\u7aef\u5728\u5e36\u5bec\u53d7\u9650\u7684\u74b0\u5883\u4e2d\u901a\u5e38\u662f\u4e0d\u5207\u5be6\u969b\u7684\uff0c\u56e0\u70ba\u50b3\u8f38\u539f\u59cb\u8996\u89ba\u6578\u64da\u6703\u5f15\u5165\u986f\u8457\u7684\u5ef6\u9072\u958b\u92b7\u3002\u96d6\u7136\u6700\u8fd1\u7684\u908a\u7de3-\u96f2\u5354\u4f5c\u67b6\u69cb\u8a66\u5716\u5728\u8a2d\u5099\u4e4b\u9593\u5283\u5206VLM\u5de5\u4f5c\u8ca0\u8f09\uff0c\u4f46\u5b83\u5011\u901a\u5e38\u4f9d\u8cf4\u65bc\u50b3\u8f38\u56fa\u5b9a\u5927\u5c0f\u7684\u8868\u793a\uff0c\u7f3a\u4e4f\u5c0d\u52d5\u614b\u7db2\u7d61\u689d\u4ef6\u7684\u9069\u61c9\u6027\uff0c\u4e26\u672a\u5145\u5206\u5229\u7528\u8a9e\u7fa9\u5197\u9918\u3002\u5728\u672c\u6587\u4e2d\uff0c\u6211\u5011\u63d0\u51fa\u4e86\u4e00\u500b\u6f38\u9032\u5f0f\u8a9e\u7fa9\u901a\u4fe1\u6846\u67b6\uff0c\u7528\u65bc\u908a\u7de3-\u96f2VLM\u63a8\u65b7\uff0c\u4f7f\u7528\u4e00\u7a2eMeta AutoEncoder\u5c07\u8996\u89ba\u6a19\u8a18\u58d3\u7e2e\u70ba\u81ea\u9069\u61c9\u7684\u3001\u6f38\u9032\u53ef\u7d30\u5316\u7684\u8868\u793a\uff0c\u5be6\u73fe\u8207\u73fe\u6210VLM\u7684\u5373\u63d2\u5373\u7528\u90e8\u7f72\uff0c\u800c\u7121\u9700\u984d\u5916\u7684\u5fae\u8abf\u3002\u9019\u7a2e\u8a2d\u8a08\u5141\u8a31\u5728\u4e0d\u540c\u4fe1\u606f\u7d1a\u5225\u9032\u884c\u9748\u6d3b\u50b3\u8f38\uff0c\u63d0\u4f9b\u901a\u4fe1\u6210\u672c\u548c\u8a9e\u7fa9\u4fdd\u771f\u5ea6\u4e4b\u9593\u7684\u53ef\u63a7\u6b0a\u8861\u3002\u6211\u5011\u5be6\u73fe\u4e86\u4e00\u500b\u5b8c\u6574\u7684\u7aef\u5230\u7aef\u908a\u7de3-\u96f2\u7cfb\u7d71\uff0c\u5305\u542b\u5d4c\u5165\u5f0fNXP i.MX95\u5e73\u53f0\u548cGPU\u4f3a\u670d\u5668\uff0c\u901a\u904e\u5e36\u5bec\u53d7\u9650\u7684\u7db2\u7d61\u9032\u884c\u901a\u4fe1\u3002\u5be6\u9a57\u7d50\u679c\u986f\u793a\uff0c\u57281 Mbps\u7684\u4e0a\u884c\u5e36\u5bec\u4e0b\uff0c\u6240\u63d0\u51fa\u7684\u6f38\u9032\u5f0f\u65b9\u6848\u986f\u8457\u6e1b\u5c11\u4e86\u7db2\u7d61\u5ef6\u9072\uff0c\u76f8\u8f03\u65bc\u5168\u908a\u7de3\u548c\u5168\u96f2\u89e3\u6c7a\u65b9\u6848\uff0c\u540c\u6642\u5728\u9ad8\u58d3\u7e2e\u4e0b\u4ecd\u4fdd\u6301\u9ad8\u8a9e\u7fa9\u4e00\u81f4\u6027\u3002\u5be6\u73fe\u4ee3\u78bc\u5c07\u5728\u767c\u8868\u6642\u91cb\u51fa\uff0c\u7db2\u5740\u70ba https://github.com/open-ep/ProSemComVLM\u3002", "author": "Cyril Shih-Huan Hsu et.al.", "authors": "Cyril Shih-Huan Hsu, Wig Yuan-Cheng Cheng, Chrysa Papagianni", "id": "2604.26508v1", "paper_url": "http://arxiv.org/abs/2604.26508v1", "repo": "null"}}