{"2606.14270": {"publish_time": "2026-06-12", "title": "Robust Fall Recovery for Armless Bipedal-Wheeled Robots Via Force-Guided Learning", "paper_summary": "Fall recovery is critical for autonomous legged locomotion. Existing methods have demonstrated that some legged robots, such as humanoids and quadrupeds, are capable of fall recovery from diverse postures by utilizing arms or coordinating multi-legs to generate support forces. Without arms or other legs to provide supportive assistance, a bipedal-wheeled robot must rely solely on the actuation of its legs, making recovery particularly difficult. To address this, we introduce FTSR (Force-guided Teacher-student framework with Stage-wise Rewards). The force-guided method constructs an external auxiliary force during simulation training that correlates directly with the robot's real-time height, explicitly formulating this force as an optimizable constraint. Through constrained reinforcement learning, the policy is guided toward reducing force dependency gradually and increasing the body height, developing internal recovery strategies despite having no arms for support. Height-progressive stage-Wise rewards progressively structure posture stabilization during recovery and transition to sustained locomotion, integrated with teacher-student architecture distilling privileged knowledge of force effects and recovery dynamics. After simulation training, the policy is deployed on a physical armless bipedal-wheeled robot and extensively evaluated. Experiments confirm robust and reliable fall recovery under diverse challenging conditions, demonstrating strong environmental adaptability and motion robustness, while maintaining full post-recovery motion capability. The framework also generalizes effectively to a high-DOF humanoid, confirming its practical generalizability. The project page is available at https://2350575870.github.io/force-guided.github.io/", "paper_summary_zh": "\u79cb\u5b63\u6062\u5fa9\u5c0d\u65bc\u81ea\u4e3b\u817f\u90e8\u904b\u52d5\u81f3\u95dc\u91cd\u8981\u3002\u73fe\u6709\u7684\u65b9\u6cd5\u5df2\u7d93\u8b49\u660e\uff0c\u4e00\u4e9b\u817f\u90e8\u6a5f\u5668\u4eba\uff0c\u5982\u4eba\u5f62\u6a5f\u5668\u4eba\u548c\u56db\u8db3\u6a5f\u5668\u4eba\uff0c\u80fd\u5920\u901a\u904e\u5229\u7528\u624b\u81c2\u6216\u5354\u8abf\u591a\u689d\u817f\u4f86\u7522\u751f\u652f\u6490\u529b\uff0c\u5f9e\u5404\u7a2e\u59ff\u52e2\u4e2d\u6062\u5fa9\u6454\u5012\u3002\u6c92\u6709\u624b\u81c2\u6216\u5176\u4ed6\u817f\u90e8\u63d0\u4f9b\u652f\u6301\u7684\u96d9\u8db3\u8f2a\u5f0f\u6a5f\u5668\u4eba\u5fc5\u9808\u50c5\u4f9d\u8cf4\u5176\u817f\u90e8\u7684\u9a45\u52d5\uff0c\u4f7f\u5f97\u6062\u5fa9\u8b8a\u5f97\u7279\u5225\u56f0\u96e3\u3002\u70ba\u4e86\u89e3\u6c7a\u9019\u500b\u554f\u984c\uff0c\u6211\u5011\u5f15\u5165\u4e86FTSR\uff08\u57fa\u65bc\u529b\u91cf\u5f15\u5c0e\u7684\u5e2b\u751f\u6846\u67b6\uff0c\u5177\u6709\u968e\u6bb5\u6027\u734e\u52f5\uff09\u3002\u9019\u7a2e\u529b\u91cf\u5f15\u5c0e\u7684\u65b9\u6cd5\u5728\u6a21\u64ec\u8a13\u7df4\u671f\u9593\u69cb\u5efa\u4e86\u4e00\u500b\u5916\u90e8\u8f14\u52a9\u529b\u91cf\uff0c\u8a72\u529b\u91cf\u8207\u6a5f\u5668\u4eba\u7684\u5be6\u6642\u9ad8\u5ea6\u76f4\u63a5\u76f8\u95dc\uff0c\u660e\u78ba\u5730\u5c07\u9019\u7a2e\u529b\u91cf\u516c\u5f0f\u5316\u70ba\u53ef\u512a\u5316\u7684\u7d04\u675f\u3002\u901a\u904e\u53d7\u7d04\u675f\u7684\u5f37\u5316\u5b78\u7fd2\uff0c\u7b56\u7565\u88ab\u5f15\u5c0e\u9010\u6b65\u6e1b\u5c11\u5c0d\u529b\u91cf\u7684\u4f9d\u8cf4\u4e26\u589e\u52a0\u8eab\u9ad4\u9ad8\u5ea6\uff0c\u5118\u7ba1\u6c92\u6709\u624b\u81c2\u652f\u6301\uff0c\u4ecd\u7136\u767c\u5c55\u51fa\u5167\u90e8\u6062\u5fa9\u7b56\u7565\u3002\u9ad8\u5ea6\u6f38\u9032\u7684\u968e\u6bb5\u6027\u734e\u52f5\u9010\u6b65\u7d50\u69cb\u5316\u6062\u5fa9\u904e\u7a0b\u4e2d\u7684\u59ff\u52e2\u7a69\u5b9a\u6027\uff0c\u4e26\u904e\u6e21\u5230\u6301\u7e8c\u904b\u52d5\uff0c\u7d50\u5408\u5e2b\u751f\u67b6\u69cb\u63d0\u7149\u529b\u91cf\u6548\u61c9\u548c\u6062\u5fa9\u52d5\u614b\u7684\u7279\u6b0a\u77e5\u8b58\u3002\u5728\u6a21\u64ec\u8a13\u7df4\u5f8c\uff0c\u8a72\u7b56\u7565\u88ab\u90e8\u7f72\u5728\u4e00\u500b\u7121\u81c2\u7684\u96d9\u8db3\u8f2a\u5f0f\u6a5f\u5668\u4eba\u4e0a\u4e26\u9032\u884c\u4e86\u5ee3\u6cdb\u8a55\u4f30\u3002\u5be6\u9a57\u78ba\u8a8d\u5728\u5404\u7a2e\u6311\u6230\u6027\u689d\u4ef6\u4e0b\u5177\u6709\u5f37\u5927\u548c\u53ef\u9760\u7684\u6454\u5012\u6062\u5fa9\u80fd\u529b\uff0c\u986f\u793a\u51fa\u5f37\u5927\u7684\u74b0\u5883\u9069\u61c9\u6027\u548c\u904b\u52d5\u7a69\u5065\u6027\uff0c\u540c\u6642\u4fdd\u6301\u5b8c\u6574\u7684\u6062\u5fa9\u5f8c\u904b\u52d5\u80fd\u529b\u3002\u8a72\u6846\u67b6\u4e5f\u6709\u6548\u5730\u63a8\u5ee3\u5230\u9ad8\u81ea\u7531\u5ea6\u7684\u4eba\u5f62\u6a5f\u5668\u4eba\uff0c\u78ba\u8a8d\u5176\u5be6\u969b\u7684\u666e\u904d\u6027\u3002\u9805\u76ee\u9801\u9762\u53ef\u5728 https://2350575870.github.io/force-guided.github.io/ \u7372\u5f97\u3002", "author": "Haidong Hou et.al.", "authors": "Haidong Hou, Zhangguo Yu, Tao Han, Hengbo Qi, Khaleel Ghazal, Yu Zhang, Yidong Du, Xuechao Chen, Fei Meng", "id": "2606.14270v1", "paper_url": "http://arxiv.org/abs/2606.14270v1", "repo": "null"}}