{"2605.16961": {"publish_time": "2026-05-16", "title": "Latent Action Control for Reasoning-Guided Unified Image Generation", "paper_summary": "Unified multimodal models can encode visual understanding and image generation within a shared backbone, yet understanding does not automatically translate into control: models may infer objects, relations, or knowledge cues but fail to instantiate them in the generated image. We propose Latent Action Control (LAC), which makes reasoning actionable by representing it as hidden continuous actions inside a unified generator. Given a prompt, LAC rolls out a role-structured latent trajectory for planning, internal visual drafting, diagnosis, and refinement, and injects these actions into the hidden stream that conditions flow-based generation, without producing reasoning tokens or intermediate images. Since such action trajectories are unobserved, LAC learns them through prior-guided variational latent action alignment from training-only rendered semantic priors, draft image features, and supervised halting signals, followed by Latent-Flow GRPO to align the latent-to-image rollout with terminal visual feedback. This provides a control path from inferred relations, bindings, and knowledge cues to the generation process. Instantiated on BAGEL-7B-MoT, LAC consistently improves compositional and knowledge-grounded generation across GenEval, WISE, and T2I-CompBench, with the largest gains on spatial relations, attribute binding, and world-knowledge-sensitive prompts. Ablations and latent interventions show that the learned action trajectory is consumed by the generator, suggesting that unified generation benefits when understanding is not only encoded, but made actionable during generation.", "paper_summary_zh": "\u7d71\u4e00\u7684\u591a\u6a21\u614b\u6a21\u578b\u53ef\u4ee5\u5728\u5171\u4eab\u7684\u9aa8\u5e79\u4e2d\u7de8\u78bc\u8996\u89ba\u7406\u89e3\u548c\u5716\u50cf\u751f\u6210\uff0c\u7136\u800c\u7406\u89e3\u4e26\u4e0d\u81ea\u52d5\u8f49\u5316\u70ba\u63a7\u5236\uff1a\u6a21\u578b\u53ef\u80fd\u63a8\u65b7\u51fa\u7269\u9ad4\u3001\u95dc\u4fc2\u6216\u77e5\u8b58\u63d0\u793a\uff0c\u4f46\u672a\u80fd\u5728\u751f\u6210\u7684\u5716\u50cf\u4e2d\u5177\u9ad4\u5316\u5b83\u5011\u3002<lb/>\u6211\u5011\u63d0\u51fa\u6f5b\u5728\u884c\u52d5\u63a7\u5236\uff08Latent Action Control\uff0cLAC\uff09\uff0c\u901a\u904e\u5c07\u63a8\u7406\u8868\u793a\u70ba\u7d71\u4e00\u751f\u6210\u5668\u5167\u90e8\u7684\u96b1\u85cf\u9023\u7e8c\u884c\u52d5\uff0c\u4f7f\u63a8\u7406\u8b8a\u5f97\u53ef\u64cd\u4f5c\u3002<lb/>\u7d66\u5b9a\u4e00\u500b\u63d0\u793a\uff0cLAC \u5c55\u958b\u4e00\u500b\u89d2\u8272\u7d50\u69cb\u5316\u7684\u6f5b\u5728\u8ecc\u8de1\uff0c\u7528\u65bc\u898f\u5283\u3001\u5167\u90e8\u8996\u89ba\u8349\u5716\u3001\u8a3a\u65b7\u548c\u6539\u9032\uff0c\u4e26\u5c07\u9019\u4e9b\u884c\u52d5\u6ce8\u5165\u5230\u689d\u4ef6\u6d41\u751f\u6210\u7684\u96b1\u85cf\u6d41\u4e2d\uff0c\u800c\u4e0d\u7522\u751f\u63a8\u7406\u6a19\u8a18\u6216\u4e2d\u9593\u5716\u50cf\u3002<lb/>\u7531\u65bc\u9019\u6a23\u7684\u884c\u52d5\u8ecc\u8de1\u662f\u4e0d\u53ef\u89c0\u5bdf\u7684\uff0cLAC \u901a\u904e\u5f9e\u50c5\u8a13\u7df4\u7684\u8a9e\u7fa9\u5148\u9a57\u3001\u8349\u5716\u5716\u50cf\u7279\u5fb5\u548c\u76e3\u7763\u505c\u6b62\u4fe1\u865f\u4e2d\u9032\u884c\u5148\u9a57\u5f15\u5c0e\u7684\u8b8a\u5206\u6f5b\u5728\u884c\u52d5\u5c0d\u9f4a\u4f86\u5b78\u7fd2\u5b83\u5011\uff0c\u96a8\u5f8c\u901a\u904e\u6f5b\u5728\u6d41 GRPO \u5c07\u6f5b\u5728\u5230\u5716\u50cf\u7684\u5c55\u958b\u8207\u7d42\u7aef\u8996\u89ba\u53cd\u994b\u5c0d\u9f4a\u3002<lb/>\u9019\u63d0\u4f9b\u4e86\u4e00\u689d\u5f9e\u63a8\u65b7\u7684\u95dc\u4fc2\u3001\u7d81\u5b9a\u548c\u77e5\u8b58\u63d0\u793a\u5230\u751f\u6210\u904e\u7a0b\u7684\u63a7\u5236\u8def\u5f91\u3002<lb/>\u5728 BAGEL-7B-MoT \u4e0a\u5be6\u73fe\u7684 LAC \u4e00\u81f4\u5730\u6539\u5584\u4e86\u5728 GenEval\u3001WISE \u548c T2I-CompBench \u4e0a\u7684\u7d44\u5408\u548c\u77e5\u8b58\u57fa\u790e\u751f\u6210\uff0c\u5728\u7a7a\u9593\u95dc\u4fc2\u3001\u5c6c\u6027\u7d81\u5b9a\u548c\u5c0d\u4e16\u754c\u77e5\u8b58\u654f\u611f\u7684\u63d0\u793a\u4e0a\u7372\u5f97\u4e86\u6700\u5927\u7684\u589e\u76ca\u3002<lb/>\u6d88\u878d\u548c\u6f5b\u5728\u5e72\u9810\u986f\u793a\u5b78\u5230\u7684\u884c\u52d5\u8ecc\u8de1\u88ab\u751f\u6210\u5668\u6d88\u8017\uff0c\u9019\u8868\u660e\u7576\u7406\u89e3\u4e0d\u50c5\u88ab\u7de8\u78bc\uff0c\u800c\u4e14\u5728\u751f\u6210\u904e\u7a0b\u4e2d\u8b8a\u5f97\u53ef\u64cd\u4f5c\u6642\uff0c\u7d71\u4e00\u751f\u6210\u53d7\u76ca\u3002", "author": "Fuxiang Zhai et.al.", "authors": "Fuxiang Zhai, Sixiang Chen, Yingjin Li, Shuaibo Li, Jianyu Lai, Tengjun Huang, Lei Zhu", "id": "2605.16961v1", "paper_url": "http://arxiv.org/abs/2605.16961v1", "repo": "null"}}