{"2405.08174": {"publish_time": "2024-05-13", "title": "Estimating Direct and Indirect Causal Effects of Spatiotemporal Interventions in Presence of Spatial Interference", "paper_summary": "Spatial interference (SI) occurs when the treatment at one location affects\nthe outcomes at other locations. Accounting for spatial interference in\nspatiotemporal settings poses further challenges as interference violates the\nstable unit treatment value assumption, making it infeasible for standard\ncausal inference methods to quantify the effects of time-varying treatment at\nspatially varying outcomes. In this paper, we first formalize the concept of\nspatial interference in case of time-varying treatment assignments by extending\nthe potential outcome framework under the assumption of no unmeasured\nconfounding. We then propose our deep learning based potential outcome model\nfor spatiotemporal causal inference. We utilize latent factor modeling to\nreduce the bias due to time-varying confounding while leveraging the power of\nU-Net architecture to capture global and local spatial interference in data\nover time. Our causal estimators are an extension of average treatment effect\n(ATE) for estimating direct (DATE) and indirect effects (IATE) of spatial\ninterference on treated and untreated data. Being the first of its kind deep\nlearning based spatiotemporal causal inference technique, our approach shows\nadvantages over several baseline methods based on the experiment results on two\nsynthetic datasets, with and without spatial interference. Our results on\nreal-world climate dataset also align with domain knowledge, further\ndemonstrating the effectiveness of our proposed method.", "paper_summary_zh": "\u7a7a\u9593\u5e72\u64fe (SI) \u662f\u6307\u67d0\u500b\u5730\u65b9\u7684\u7642\u6cd5\u6703\u5f71\u97ff\u5176\u4ed6\u5730\u65b9\u7684\u7d50\u679c\u3002\u5728\u6642\u7a7a\u80cc\u666f\u4e0b\u8003\u616e\u7a7a\u9593\u5e72\u64fe\u6703\u5e36\u4f86\u9032\u4e00\u6b65\u7684\u6311\u6230\uff0c\u56e0\u70ba\u5e72\u64fe\u6703\u9055\u53cd\u7a69\u5b9a\u7684\u55ae\u4f4d\u6cbb\u7642\u503c\u5047\u8a2d\uff0c\u4f7f\u5f97\u6a19\u6e96\u56e0\u679c\u63a8\u8ad6\u65b9\u6cd5\u7121\u6cd5\u91cf\u5316\u6642\u8b8a\u6cbb\u7642\u5c0d\u7a7a\u9593\u8b8a\u7570\u7d50\u679c\u7684\u5f71\u97ff\u3002\u5728\u672c\u6587\u4e2d\uff0c\u6211\u5011\u9996\u5148\u5728\u6c92\u6709\u672a\u6e2c\u91cf\u6df7\u6dc6\u7684\u5047\u8a2d\u4e0b\uff0c\u900f\u904e\u64f4\u5c55\u6f5b\u5728\u7d50\u679c\u67b6\u69cb\uff0c\u5c07\u6642\u8b8a\u6cbb\u7642\u5206\u914d\u7684\u7a7a\u9593\u5e72\u64fe\u6982\u5ff5\u5f62\u5f0f\u5316\u3002\u63a5\u8457\uff0c\u6211\u5011\u63d0\u51fa\u57fa\u65bc\u6df1\u5ea6\u5b78\u7fd2\u7684\u6f5b\u5728\u7d50\u679c\u6a21\u578b\uff0c\u7528\u65bc\u6642\u7a7a\u56e0\u679c\u63a8\u8ad6\u3002\u6211\u5011\u5229\u7528\u6f5b\u5728\u56e0\u5b50\u6a21\u578b\u4f86\u6e1b\u5c11\u56e0\u6642\u8b8a\u6df7\u6dc6\u9020\u6210\u7684\u504f\u5dee\uff0c\u540c\u6642\u5229\u7528 U-Net \u67b6\u69cb\u7684\u512a\u52e2\u4f86\u64f7\u53d6\u8cc7\u6599\u4e2d\u96a8\u6642\u9593\u8b8a\u5316\u7684\u5168\u5c40\u548c\u5c40\u90e8\u7a7a\u9593\u5e72\u64fe\u3002\u6211\u5011\u7684\u56e0\u679c\u4f30\u8a08\u5668\u662f\u5e73\u5747\u6cbb\u7642\u6548\u679c (ATE) \u7684\u5ef6\u4f38\uff0c\u7528\u65bc\u4f30\u8a08\u7a7a\u9593\u5e72\u64fe\u5c0d\u5df2\u6cbb\u7642\u548c\u672a\u6cbb\u7642\u8cc7\u6599\u7684\u76f4\u63a5 (DATE) \u548c\u9593\u63a5\u6548\u679c (IATE)\u3002\u4f5c\u70ba\u9996\u5275\u57fa\u65bc\u6df1\u5ea6\u5b78\u7fd2\u7684\u6642\u7a7a\u56e0\u679c\u63a8\u8ad6\u6280\u8853\uff0c\u6211\u5011\u7684\u505a\u6cd5\u5728\u5169\u500b\u5408\u6210\u8cc7\u6599\u96c6\uff08\u6709\u548c\u6c92\u6709\u7a7a\u9593\u5e72\u64fe\uff09\u7684\u5be6\u9a57\u7d50\u679c\u4e2d\uff0c\u5c55\u73fe\u51fa\u512a\u65bc\u591a\u7a2e\u57fa\u7dda\u65b9\u6cd5\u7684\u512a\u52e2\u3002\u6211\u5011\u5728\u771f\u5be6\u4e16\u754c\u6c23\u5019\u8cc7\u6599\u96c6\u7684\u7d50\u679c\u4e5f\u8207\u9818\u57df\u77e5\u8b58\u4e00\u81f4\uff0c\u9032\u4e00\u6b65\u8b49\u660e\u6211\u5011\u63d0\u51fa\u7684\u65b9\u6cd5\u7684\u6709\u6548\u6027\u3002", "author": "Sahara Ali et.al.", "authors": "Sahara Ali, Omar Faruque, Jianwu Wang", "id": "2405.08174v1", "paper_url": "http://arxiv.org/abs/2405.08174v1", "repo": "null"}}